aiaas_rec/.DS_Store
aiaas_rec/__init__.py
aiaas_rec/datasets/.DS_Store
aiaas_rec/datasets/__init__.py
aiaas_rec/datasets/amazon_reviews.py
aiaas_rec/datasets/cosmos_cli.py
aiaas_rec/datasets/covid_utils.py
aiaas_rec/datasets/criteo.py
aiaas_rec/datasets/download_utils.py
aiaas_rec/datasets/mind.py
aiaas_rec/datasets/movielens.py
aiaas_rec/datasets/pandas_df_utils.py
aiaas_rec/datasets/python_splitters.py
aiaas_rec/datasets/spark_splitters.py
aiaas_rec/datasets/sparse.py
aiaas_rec/datasets/split_utils.py
aiaas_rec/datasets/wikidata.py
aiaas_rec/evaluation/.DS_Store
aiaas_rec/evaluation/__init__.py
aiaas_rec/evaluation/python_evaluation.py
aiaas_rec/evaluation/spark_evaluation.py
aiaas_rec/models/.DS_Store
aiaas_rec/models/__init__.py
aiaas_rec/models/cornac/__init__.py
aiaas_rec/models/cornac/cornac_utils.py
aiaas_rec/models/deeprec/__init__.py
aiaas_rec/models/deeprec/deeprec_utils.py
aiaas_rec/models/deeprec/DataModel/ImplicitCF.py
aiaas_rec/models/deeprec/DataModel/__init__.py
aiaas_rec/models/deeprec/io/__init__.py
aiaas_rec/models/deeprec/io/dkn_item2item_iterator.py
aiaas_rec/models/deeprec/io/dkn_iterator.py
aiaas_rec/models/deeprec/io/iterator.py
aiaas_rec/models/deeprec/io/nextitnet_iterator.py
aiaas_rec/models/deeprec/io/sequential_iterator.py
aiaas_rec/models/deeprec/models/__init__.py
aiaas_rec/models/deeprec/models/base_model.py
aiaas_rec/models/deeprec/models/dkn.py
aiaas_rec/models/deeprec/models/dkn_item2item.py
aiaas_rec/models/deeprec/models/xDeepFM.py
aiaas_rec/models/deeprec/models/graphrec/__init__.py
aiaas_rec/models/deeprec/models/graphrec/lightgcn.py
aiaas_rec/models/deeprec/models/sequential/__init__.py
aiaas_rec/models/deeprec/models/sequential/asvd.py
aiaas_rec/models/deeprec/models/sequential/caser.py
aiaas_rec/models/deeprec/models/sequential/chicken.py
aiaas_rec/models/deeprec/models/sequential/gru4rec.py
aiaas_rec/models/deeprec/models/sequential/nextitnet.py
aiaas_rec/models/deeprec/models/sequential/rnn_cell_implement.py
aiaas_rec-0.0.4.dist-info/METADATA
aiaas_rec-0.0.4.dist-info/WHEEL
aiaas_rec-0.0.4.dist-info/licenses/LICENSE
aiaas_rec-0.0.4.dist-info/RECORD
